bait/__init__.py
bait/bait.py
bait/bait_customtests.py
bait/bait_errors.py
bait/bait_plot.py
bait-2.5.9.dist-info/LICENSE.md
bait-2.5.9.dist-info/METADATA
bait-2.5.9.dist-info/WHEEL
bait-2.5.9.dist-info/top_level.txt
bait-2.5.9.dist-info/RECORD
