Metadata-Version: 2.1
Name: bait
Version: 2.5.9
Summary: an ITerative BAer picker algorithm
Home-page: https://github.com/mbagagli/bait
Author: Matteo Bagagli
Author-email: matteo.bagagli@ingv.it
License: UNKNOWN
Platform: UNKNOWN
Classifier: Programming Language :: Python :: 3
Classifier: License :: OSI Approved :: GNU General Public License v3 (GPLv3)
Classifier: Operating System :: Unix
Classifier: Operating System :: MacOS
Classifier: Intended Audience :: Science/Research
Requires-Python: >=3.6
License-File: LICENSE.md
Requires-Dist: PyYAML (>=3.13)
Requires-Dist: matplotlib (>=2.1.0)
Requires-Dist: obspy (>=1.1.0)
